tg2fa_translit/__init__.py
tg2fa_translit/convert.py
tg2fa_translit/decode.py
tg2fa_translit/model_2.9.zip
tg2fa_translit/transformer.py
tg2fa_translit-1.0.dist-info/METADATA
tg2fa_translit-1.0.dist-info/WHEEL
tg2fa_translit-1.0.dist-info/top_level.txt
tg2fa_translit-1.0.dist-info/RECORD
