Metadata-Version: 2.1
Name: tg2fa_translit
Version: 1.0
Summary: Translate Tajik texts to Persian with the help of a seq2seq model
Author: stibiumghost
